setup.cfg
setup.py
PorkofQRCode/PorkofQRCode.py
PorkofQRCode/__init__.py
PorkofQRCode.egg-info/PKG-INFO
PorkofQRCode.egg-info/SOURCES.txt
PorkofQRCode.egg-info/dependency_links.txt
PorkofQRCode.egg-info/not-zip-safe
PorkofQRCode.egg-info/requires.txt
PorkofQRCode.egg-info/top_level.txt